hybridbackend/libhybridbackend.so
hybridbackend/__init__.py
hybridbackend/run.py
hybridbackend/common/test.py
hybridbackend/common/__init__.py
hybridbackend/torch/__init__.py
hybridbackend/tensorflow/wraps.py
hybridbackend/tensorflow/libhybridbackend_tensorflow.so
hybridbackend/tensorflow/__init__.py
hybridbackend/tensorflow/data/iterators.py
hybridbackend/tensorflow/data/__init__.py
hybridbackend/tensorflow/data/validate.py
hybridbackend/tensorflow/data/dataframe.py
hybridbackend/tensorflow/data/rebatch/__init__.py
hybridbackend/tensorflow/data/rebatch/dataset_v1.py
hybridbackend/tensorflow/data/rebatch/dataset.py
hybridbackend/tensorflow/data/rebatch/dataset_v2.py
hybridbackend/tensorflow/data/sync/__init__.py
hybridbackend/tensorflow/data/sync/hook.py
hybridbackend/tensorflow/data/sync/dataset_v1.py
hybridbackend/tensorflow/data/sync/dataset.py
hybridbackend/tensorflow/data/sync/dataset_v2.py
hybridbackend/tensorflow/data/tabular/table.py
hybridbackend/tensorflow/data/tabular/__init__.py
hybridbackend/tensorflow/data/tabular/dataset_v1.py
hybridbackend/tensorflow/data/tabular/dataset.py
hybridbackend/tensorflow/data/tabular/dataset_v2.py
hybridbackend/tensorflow/data/prefetch/__init__.py
hybridbackend/tensorflow/data/prefetch/iterator.py
hybridbackend/tensorflow/estimator/estimator.py
hybridbackend/tensorflow/estimator/__init__.py
hybridbackend/tensorflow/pipeline/benchmark.py
hybridbackend/tensorflow/pipeline/pipeline_lib.py
hybridbackend/tensorflow/pipeline/__init__.py
hybridbackend/tensorflow/keras/model.py
hybridbackend/tensorflow/keras/__init__.py
hybridbackend/tensorflow/keras/layers/__init__.py
hybridbackend/tensorflow/ops/__init__.py
hybridbackend/tensorflow/ops/unique/benchmark.py
hybridbackend/tensorflow/ops/unique/__init__.py
hybridbackend/tensorflow/ops/sparse/__init__.py
hybridbackend/tensorflow/ops/sparse/count_nonzero/ops.py
hybridbackend/tensorflow/ops/sparse/count_nonzero/benchmark.py
hybridbackend_deeprec2212_cu114-0.8.0.dev1679289143.dist-info/top_level.txt
hybridbackend_deeprec2212_cu114-0.8.0.dev1679289143.dist-info/RECORD
hybridbackend_deeprec2212_cu114-0.8.0.dev1679289143.dist-info/NOTICE
hybridbackend_deeprec2212_cu114-0.8.0.dev1679289143.dist-info/LICENSE
hybridbackend_deeprec2212_cu114-0.8.0.dev1679289143.dist-info/METADATA
hybridbackend_deeprec2212_cu114-0.8.0.dev1679289143.dist-info/WHEEL
